algotom/__init__.py
algotom/io/__init__.py
algotom/io/converter.py
algotom/io/loadersaver.py
algotom/post/__init__.py
algotom/post/postprocessing.py
algotom/prep/__init__.py
algotom/prep/calculation.py
algotom/prep/conversion.py
algotom/prep/correction.py
algotom/prep/filtering.py
algotom/prep/phase.py
algotom/prep/removal.py
algotom/rec/__init__.py
algotom/rec/reconstruction.py
algotom/rec/vertrec.py
algotom/util/__init__.py
algotom/util/calibration.py
algotom/util/correlation.py
algotom/util/simulation.py
algotom/util/utility.py
algotom-1.7.0.dist-info/METADATA
algotom-1.7.0.dist-info/WHEEL
algotom-1.7.0.dist-info/top_level.txt
algotom-1.7.0.dist-info/RECORD
