Metadata-Version: 2.4
Name: algotom
Version: 1.7.0
Summary: Data processing algorithms for tomography
Author-email: Nghia Vo <nvo@bnl.gov>
License:                                  Apache License
Keywords: Parallel-beam Computed Tomography,Image Processing,Tomography,X-ray Imaging,Phase Contrast Imaging,Ring artifact removal
Classifier: Programming Language :: Python :: 3
Classifier: Intended Audience :: Science/Research
Classifier: Operating System :: OS Independent
Classifier: Natural Language :: English
Classifier: Topic :: Scientific/Engineering :: Image Processing
Requires-Python: >=3.9
Requires-Dist: numpy>=1.18
Requires-Dist: scipy>=1.6
Requires-Dist: numba
Requires-Dist: pywavelets
Requires-Dist: pillow
Requires-Dist: h5py
Requires-Dist: joblib
